VisualStudioCodeGuide/README.md
VisualStudioCodeGuide/__init__.py
VisualStudioCodeGuide/__main__.py
VisualStudioCodeGuide/file.epub
VisualStudioCodeGuide/index.html
VisualStudioCodeGuide/css/__init__.py
VisualStudioCodeGuide/css/annotations.css
VisualStudioCodeGuide/css/main.css
VisualStudioCodeGuide/css/normalize.css
VisualStudioCodeGuide/css/popup.css
VisualStudioCodeGuide/font/__init__.py
VisualStudioCodeGuide/font/fontello.eot
VisualStudioCodeGuide/font/fontello.svg
VisualStudioCodeGuide/font/fontello.ttf
VisualStudioCodeGuide/font/fontello.woff
VisualStudioCodeGuide/img/__init__.py
VisualStudioCodeGuide/img/annotator-glyph-sprite.png
VisualStudioCodeGuide/img/annotator-icon-sprite.png
VisualStudioCodeGuide/img/apple-touch-icon.png
VisualStudioCodeGuide/img/cancelfullscreen.png
VisualStudioCodeGuide/img/close.png
VisualStudioCodeGuide/img/fullscreen.png
VisualStudioCodeGuide/img/loader.gif
VisualStudioCodeGuide/img/menu-icon.png
VisualStudioCodeGuide/img/save.png
VisualStudioCodeGuide/img/saved.png
VisualStudioCodeGuide/img/settings-s.png
VisualStudioCodeGuide/img/settings.png
VisualStudioCodeGuide/img/star.png
VisualStudioCodeGuide/js/__init__.py
VisualStudioCodeGuide/js/epub.js
VisualStudioCodeGuide/js/epub.min.js
VisualStudioCodeGuide/js/epub.min.map
VisualStudioCodeGuide/js/hooks.min.js
VisualStudioCodeGuide/js/hooks.min.map
VisualStudioCodeGuide/js/reader.js
VisualStudioCodeGuide/js/reader.js.map
VisualStudioCodeGuide/js/reader.min.js
VisualStudioCodeGuide/js/reader.min.map
VisualStudioCodeGuide/js/hooks/__init__.py
VisualStudioCodeGuide/js/hooks/extensions/__init__.py
VisualStudioCodeGuide/js/hooks/extensions/highlight.js
VisualStudioCodeGuide/js/libs/__init__.py
VisualStudioCodeGuide/js/libs/jquery.min.js
VisualStudioCodeGuide/js/libs/localforage.min.js
VisualStudioCodeGuide/js/libs/screenfull.js
VisualStudioCodeGuide/js/libs/screenfull.min.js
VisualStudioCodeGuide/js/libs/zip.min.js
VisualStudioCodeGuide/js/plugins/__init__.py
visual_studio_code_guide-2024.3.2.0.dist-info/METADATA
visual_studio_code_guide-2024.3.2.0.dist-info/WHEEL
visual_studio_code_guide-2024.3.2.0.dist-info/entry_points.txt
visual_studio_code_guide-2024.3.2.0.dist-info/top_level.txt
visual_studio_code_guide-2024.3.2.0.dist-info/RECORD
